Metadata-Version: 2.1
Name: taskmgr
Version: 0.0.0.post1
Summary: taskmgr - A simple to use task manager
Home-page: https://gitlab.com/dsikes/taskmgr
Author: Dan Sikes
Author-email: dansikes7@gmail.com
License: UNKNOWN
Project-URL: Source, https://gitlab.com/dsikes/taskmgr
Keywords: task manager,automation
Platform: UNKNOWN
